{
  "heroSection": {
    "badgeText": "¿Quieres cambiar el miedo por seguridad?",
    "titleAccent": "Reaprende",
    "titleNormal": " las matemáticas",
    "description": "Curso de nivelación en matemáticas diseñado para comprender los contenidos desde cero.",
    "buttonText": "Reserva tu cupo"
  },
  "targetAudienceSection": {
    "title": "🤔 ¿Para quién es este curso?",
    "profiles": {
      "title": "👉 Si eres...",
      "list": [
        {
          "title": "Estudiante",
          "descriptions": [
            "Estás en enseñanza media (1° a 4° medio) buscando fortalecer tus habilidades matemáticas.",
            "Te estás preparando para la PAES 2024."
          ]
        },

        {
          "title": "Profesional o Egresado",
          "descriptions": [
            "Necesitas mejorar tu comprensión matemática.",
            "Estás considerando estudiar una nueva carrera."
          ]
        },

        {
          "title": "Docente",
          "descriptions": ["Quieres aprender nuevas estrategias de enseñanza."]
        }
      ]
    },
    "goals": {
      "title": "✅ Y quieres...",
      "list": [
        "Saber qué hacer, cómo y por qué frente a cualquier ejercicio matemático.",
        "Tener estrategias para resolver ejercicios de manera efectiva y eficiente.",
        "Reconocer patrones y representarlos de forma numérica y algebraica.",
        "Reconocer tus errores como elementos valiosos del proceso de aprendizaje.",
        "Aprender nuevos contenidos de forma autónoma.",
        "Ser reflexivo y crítico con los problemas matemáticos."
      ]
    },
    "footer": "Si te identificas con alguna de estas descripciones, este curso es para ti.",
    "buttonText": "Inscríbete ahora"
  },
  "methodologySection": {
    "title": "📖 Metodología de aprendizaje",
    "description": "Aprende desde la reflexión, la curiosidad y la aplicación práctica para un aprendizaje efectivo y emocionante.",
    "features": [
      {
        "title": "Estimular la curiosidad",
        "description": "Utilizar la curiosidad como una herramienta para impulsar el aprendizaje, motivando a los estudiantes a preguntar y explorar.",
        "icon": "Lightbulb"
      },
      {
        "title": "Aprendizaje activo",
        "description": "Los alumnos construyen activamente su conocimiento, integrando la nueva información con sus conocimientos previos.",
        "icon": "TestTubeDiagonal"
      },
      {
        "title": "Reconocimiento de patrones",
        "description": "Fomentar la exploración de patrones para identificar relaciones y conexiones en el contenido matemático.",
        "icon": "BrainCircuit"
      },
      {
        "title": "Aplicación y modelado",
        "description": "Enseñar a modelar fórmulas, pasando del lenguaje natural al lenguaje algebraico y matemático, aplicando el contenido a contextos prácticos.",
        "icon": "PencilRuler"
      },
      {
        "title": "Reflexión sobre el error",
        "description": "Prestar atención a los errores cometidos para comprender su origen y aprender de ellos.",
        "icon": "ShieldAlert"
      },
      {
        "title": "Exploración emocional",
        "description": "Integrar las emociones en el proceso de aprendizaje para hacerlo más significativo y memorable.",
        "icon": "HeartHandshake"
      }
    ]
  },
  "learningRouteSection": {
    "title": "🚀 Ruta de Aprendizaje",
    "description": "El curso se compone de 4 niveles, diseñados de manera progresiva para una comprensión integral de las matemáticas.",
    "imagePath": "/landing/learning-route.png",
    "steps": [
      {
        "color": "blue",
        "title": "Números",
        "description": "Entenderás la lógica y las bases de las matemáticas",
        "details": [
          {
            "type": "paragraph",
            "content": "Aprenderás a operar (sumar, restar, multiplicar y dividir) todos los tipos de números:"
          },
          {
            "type": "list",
            "items": [
              "Negativos y positivos",
              "Potencias y raíces",
              "Fracciones y decimales",
              "Porcentaje"
            ]
          },
          {
            "type": "paragraph",
            "content": "Además de aprender:"
          },

          {
            "type": "list",
            "items": ["Razones", "Proporcionalidad directa e inversa"]
          },
          {
            "type": "paragraph",
            "content": "Junto con sus propiedades y aplicaciones"
          }
        ]
      },
      {
        "color": "green",
        "title": "Álgebra y funciones",
        "description": "Expande tu comprensión de las matemáticas más allá de números",
        "details": [
          {
            "type": "paragraph",
            "content": "Identificarás patrones y relaciones algebraicas:"
          },
          {
            "type": "list",
            "items": [
              "Expresiones algebraicas",
              "Reducción de términos",
              "Productos notables",
              "Ecuación y función lineal",
              "Sistema de ecuaciones",
              "Ecuación y función cuadrática"
            ]
          }
        ]
      },
      {
        "color": "yellow",
        "title": "Geometría",
        "description": "Desarrollarás una comprensión visual y espacial de las matemáticas",
        "details": [
          {
            "type": "paragraph",
            "content": "Podrás reconocer cómo se construyen las fórmulas de:"
          },
          {
            "type": "list",
            "items": [
              "Perímetro, área de figuras geométricas",
              "Área y perímetro del círculo.",
              "Volumen de cuerpos geométricos",
              "Teorema de Pitágoras"
            ]
          },
          {
            "type": "paragraph",
            "content": "Además de aprender:"
          },

          {
            "type": "list",
            "items": ["Vectores", "Transformaciones isométricas"]
          }
        ]
      },
      {
        "color": "red",
        "title": "Probabilidades y estadística",
        "description": "Utilizarás TODO lo anterior para comunicar información",
        "details": [
          {
            "type": "paragraph",
            "content": "Ordenarás y clasificarás los datos para obtener información:"
          },
          {
            "type": "list",
            "items": [
              "Medidas de tendencia central (datos agrupados y desagrupados)",
              "Gráficos y tablas",
              "Medidas de posición",
              "Diagrama de cajón",
              "Regla de Laplace",
              "Probabilidades"
            ]
          }
        ]
      }
    ]
  },

  "stepsSection": {
    "title": "Comienza Ahora...",
    "description": "Lorem ipsum dolor sit, amet consectetur adipisicing elit. Eius?",
    "steps": [
      {
        "step": "Paso 1",
        "title": "Regístrate",
        "description": "Una vez completado tu registro podrás acceder a los talleres."
      },
      {
        "step": "Paso 2",
        "title": "Escoge tu Modalidad",
        "description": "Puedes tomar los talleres de manera individual o tomar la ruta completa."
      },
      {
        "step": "Paso 3",
        "title": "Accede a los Talleres",
        "description": "Podrás acceder a los talleres y comenzar tu aprendizaje."
      }
    ]
  },
  "testimonialsSection": {
    "title": "Testimonios",
    "items": [
      {
        "name": "Juan",
        "description": "Estudiante de 4to medio",
        "testimonial": "La profe cambió mi perspectiva sobre las matemáticas."
      },
      {
        "name": "María",
        "description": "Estudiante universitaria",
        "testimonial": "Gracias a este curso, ahora me siento confiada en mis habilidades matemáticas."
      }
    ]
  },
  "modalitiesSection": {
    "title": "Elige tu Camino de Aprendizaje",
    "items": [
      {
        "name": "Grabado",
        "description": "Clases grabadas, consultas ilimitadas por WhatsApp, material descargable y videos complementarios.",
        "price": "$45,000/mes",
        "features": ["Sesiones grabadas", "Acompañamiento por Whatsapp"]
      },
      {
        "name": "En Vivo",
        "description": "Clases en Zoom, consultas ilimitadas por WhatsApp, acceso a maratones PAES y material descargable.",
        "price": "$65,000/mes",
        "features": [
          "Sesiones en vivo",
          "Acompañamiento por Whatsapp",
          "Resolución de dudas en tiempo real"
        ]
      }
    ]
  },

  "whoAmISection": {
    "title": "¿Quién Soy?",
    "description": "Hola, soy [Nombre], tu instructor y mentor en esta jornada de aprendizaje. Estoy aquí para ayudarte a descubrir y potenciar tus habilidades matemáticas.",
    "imageAlt": "Imagen del instructor"
  }
}
